odoo/addons/partner_purchase_manager/README.rst
odoo/addons/partner_purchase_manager/__init__.py
odoo/addons/partner_purchase_manager/__manifest__.py
odoo/addons/partner_purchase_manager/i18n/es.po
odoo/addons/partner_purchase_manager/i18n/it.po
odoo/addons/partner_purchase_manager/i18n/partner_purchase_manager.pot
odoo/addons/partner_purchase_manager/models/__init__.py
odoo/addons/partner_purchase_manager/models/res_partner.py
odoo/addons/partner_purchase_manager/readme/CONTRIBUTORS.md
odoo/addons/partner_purchase_manager/readme/DESCRIPTION.md
odoo/addons/partner_purchase_manager/readme/USAGE.md
odoo/addons/partner_purchase_manager/static/description/icon.png
odoo/addons/partner_purchase_manager/static/description/index.html
odoo/addons/partner_purchase_manager/views/res_partner_view.xml
odoo_addon_partner_purchase_manager-18.0.1.0.0.2.dist-info/METADATA
odoo_addon_partner_purchase_manager-18.0.1.0.0.2.dist-info/WHEEL
odoo_addon_partner_purchase_manager-18.0.1.0.0.2.dist-info/top_level.txt
odoo_addon_partner_purchase_manager-18.0.1.0.0.2.dist-info/RECORD
